pyTMD/__init__.py
pyTMD/astro.py
pyTMD/compute.py
pyTMD/constituents.py
pyTMD/ellipse.py
pyTMD/interpolate.py
pyTMD/math.py
pyTMD/predict.py
pyTMD/spatial.py
pyTMD/tools.py
pyTMD/utilities.py
pyTMD/version.py
pyTMD/data/ct1971_tab6.txt
pyTMD/data/cte1973_tab.txt
pyTMD/data/d1921_tab.txt
pyTMD/data/database.json
pyTMD/data/doodson.json
pyTMD/data/hw1995_tab.txt
pyTMD/data/re14_tab3.txt
pyTMD/data/t1987_tab.txt
pyTMD/data/tab5.2e.txt
pyTMD/data/tab5.3a.txt
pyTMD/data/tab5.3b.txt
pyTMD/data/w1990_tab.txt
pyTMD/datasets/__init__.py
pyTMD/datasets/fetch_arcticdata.py
pyTMD/datasets/fetch_aviso_fes.py
pyTMD/datasets/fetch_box_tpxo.py
pyTMD/datasets/fetch_gsfc_got.py
pyTMD/datasets/fetch_iers_opole.py
pyTMD/datasets/fetch_jpl_ssd.py
pyTMD/datasets/fetch_test_data.py
pyTMD/datasets/reduce_otis.py
pyTMD/io/ATLAS.py
pyTMD/io/FES.py
pyTMD/io/GOT.py
pyTMD/io/IERS.py
pyTMD/io/NOAA.py
pyTMD/io/OTIS.py
pyTMD/io/__init__.py
pyTMD/io/dataset.py
pyTMD/io/model.py
pyTMD/solve/__init__.py
pyTMD/solve/constants.py
pytmd-3.0.2.dist-info/licenses/LICENSE
pytmd-3.0.2.dist-info/METADATA
pytmd-3.0.2.dist-info/WHEEL
pytmd-3.0.2.dist-info/entry_points.txt
pytmd-3.0.2.dist-info/top_level.txt
pytmd-3.0.2.dist-info/RECORD
