Metadata-Version: 2.4
Name: pyTMD
Version: 3.0.2
Summary: Python-based tidal prediction software for estimating ocean, load, solid Earth and pole tides
Author: Tyler Sutterley
Author-email: tsutterl@uw.edu
Maintainer: pyTMD contributors
License: MIT License
Project-URL: Homepage, https://pytmd.readthedocs.io
Project-URL: Documentation, https://pytmd.readthedocs.io
Project-URL: Repository, https://github.com/pyTMD/pyTMD
Project-URL: Issues, https://github.com/pyTMD/pyTMD/issues
Keywords: Ocean Tides,Load Tides,Pole Tides,Solid Earth Tides,Tidal Prediction
Classifier: Development Status :: 3 - Alpha
Classifier: Intended Audience :: Science/Research
Classifier: License :: OSI Approved :: MIT License
Classifier: Operating System :: OS Independent
Classifier: Programming Language :: Python :: 3
Classifier: Programming Language :: Python :: 3.9
Classifier: Programming Language :: Python :: 3.10
Classifier: Programming Language :: Python :: 3.11
Classifier: Programming Language :: Python :: 3.12
Classifier: Programming Language :: Python :: 3.13
Classifier: Programming Language :: Python :: 3.14
Classifier: Topic :: Scientific/Engineering :: Physics
Classifier: Topic :: Scientific/Engineering :: Oceanography
Requires-Python: ~=3.9
License-File: LICENSE
Requires-Dist: h5netcdf
Requires-Dist: lxml
Requires-Dist: numpy
Requires-Dist: pint
Requires-Dist: platformdirs
Requires-Dist: pyproj>=2.5.0
Requires-Dist: scipy>=1.10.1
Requires-Dist: timescale>=0.0.8
Requires-Dist: xarray
Provides-Extra: doc
Requires-Dist: docutils; extra == "doc"
Requires-Dist: graphviz; extra == "doc"
Requires-Dist: ipympl; extra == "doc"
Requires-Dist: myst-nb; extra == "doc"
Requires-Dist: numpydoc; extra == "doc"
Requires-Dist: sphinx; extra == "doc"
Requires-Dist: sphinx-argparse>=0.4; extra == "doc"
Requires-Dist: sphinxcontrib-bibtex; extra == "doc"
Requires-Dist: sphinx-design; extra == "doc"
Requires-Dist: sphinx_rtd_theme; extra == "doc"
Provides-Extra: all
Requires-Dist: cartopy; extra == "all"
Requires-Dist: ipyleaflet; extra == "all"
Requires-Dist: ipywidgets; extra == "all"
Requires-Dist: jplephem; extra == "all"
Requires-Dist: jupyterlab; extra == "all"
Requires-Dist: matplotlib; extra == "all"
Requires-Dist: notebook; extra == "all"
Requires-Dist: pandas; extra == "all"
Provides-Extra: aws
Requires-Dist: dask; extra == "aws"
Requires-Dist: obstore; extra == "aws"
Requires-Dist: pandas; extra == "aws"
Requires-Dist: pyarrow; extra == "aws"
Requires-Dist: s3fs; extra == "aws"
Requires-Dist: zarr>=3; extra == "aws"
Provides-Extra: dev
Requires-Dist: dask; extra == "dev"
Requires-Dist: flake8; extra == "dev"
Requires-Dist: gh; extra == "dev"
Requires-Dist: oct2py; extra == "dev"
Requires-Dist: pytest>=4.6; extra == "dev"
Requires-Dist: pytest-cov; extra == "dev"
Requires-Dist: pytest-xdist; extra == "dev"
Dynamic: license-file
